README.md
setup.cfg
setup.py
pyLion/__init__.py
pyLion/__main__.py
pyLion/utils.py
pyLion/version.py
pyLion/dB/__init__.py
pyLion/dB/core.py
pyLion/dB/database.py
pyLion/functions/_FastTelethon.py
pyLion/functions/__init__.py
pyLion/functions/all.py
pyLion/functions/antiflood_db.py
pyLion/functions/asst_fns.py
pyLion/functions/blacklist_db.py
pyLion/functions/botchat_db.py
pyLion/functions/broadcast_db.py
pyLion/functions/ch_db.py
pyLion/functions/clean_db.py
pyLion/functions/echo_db.py
pyLion/functions/filter_db.py
pyLion/functions/forcesub_db.py
pyLion/functions/gban_mute_db.py
pyLion/functions/goodbye_db.py
pyLion/functions/google_image.py
pyLion/functions/logusers_db.py
pyLion/functions/mute_db.py
pyLion/functions/notes_db.py
pyLion/functions/pmpermit_db.py
pyLion/functions/snips_db.py
pyLion/functions/sudos.py
pyLion/functions/vc_sudos.py
pyLion/functions/warn_db.py
pyLion/functions/welcome_db.py
pyLion/functions/ytdl.py
pyLion/misc/__init__.py
pyLion/misc/_assistant.py
pyLion/misc/_decorators.py
pyLion/misc/_supporter.py
pyLion/misc/_wrappers.py
py_Lion.egg-info/PKG-INFO
py_Lion.egg-info/SOURCES.txt
py_Lion.egg-info/dependency_links.txt
py_Lion.egg-info/requires.txt
py_Lion.egg-info/top_level.txt