Metadata-Version: 2.1
Name: py-Lion
Version: 1.0.0
Summary: A Secure and Powerful Python-Telethon Based Library For Lion-X Userbot.
Home-page: https://github.com/TeamLion-X/Lion-x
Author: TeamLion
Author-email: jtatagaga@gmail.com
License: GNU AFFERO GENERAL PUBLIC LICENSE (v3)
Platform: UNKNOWN
Classifier: Programming Language :: Python :: 3
Classifier: License :: OSI Approved :: GNU General Public License v3 (GPLv3)
Classifier: Operating System :: OS Independent
Requires-Python: >=3.6
